docex/__init__.py
docex/core/__init__.py
docex/core/pipeline.py
docex/loaders/__init__.py
docex/loaders/base_loader.py
docex/loaders/pdf_loader.py
docex/models/__init__.py
docex/models/document.py
docex/processors/__init__.py
docex/processors/base_processor.py
docex/processors/llm_processor.py
docex_llm-0.1.1.dist-info/LICENSE
docex_llm-0.1.1.dist-info/METADATA
docex_llm-0.1.1.dist-info/WHEEL
docex_llm-0.1.1.dist-info/RECORD
