Metadata-Version: 2.1
Name: docex-llm
Version: 0.1.1
Summary: Dead simple document extraction OCR powered by LLMs
Home-page: https://github.com/archerprotect/docex
License: MIT
Keywords: ocr,document,extraction,llm,ai,pdf,vision
Author: Francisco Rubin Capalbo
Author-email: fran@archerprotect.com
Requires-Python: >=3.9,<4.0
Classifier: Development Status :: 4 - Beta
Classifier: Intended Audience :: Developers
Classifier: License :: OSI Approved :: MIT License
Classifier: Programming Language :: Python :: 3
Classifier: Programming Language :: Python :: 3.9
Classifier: Programming Language :: Python :: 3.10
Classifier: Programming Language :: Python :: 3.11
Classifier: Programming Language :: Python :: 3.12
Classifier: Programming Language :: Python :: 3.13
Classifier: Topic :: Multimedia :: Graphics :: Capture :: Scanners
Classifier: Topic :: Scientific/Engineering :: Artificial Intelligence
Classifier: Topic :: Text Processing
Requires-Dist: litellm (>=1.71.1,<2.0.0)
Requires-Dist: pdf2image (>=1.17.0,<2.0.0)
Requires-Dist: pillow (>=11.2.1,<12.0.0)
Requires-Dist: pydantic (>=2.11.5,<3.0.0)
Requires-Dist: pypdf2 (>=3.0.1,<4.0.0)
Project-URL: Documentation, https://github.com/archerprotect/docex#readme
Project-URL: Repository, https://github.com/archerprotect/docex
